Metadata-Version: 2.1
Name: HQProxy
Version: 2.0.0
Summary: HQ Trivia Proxy UK & USA
Home-page: https://github.com/Technology-cell/HQProxy
Author: Technology-cell
Author-email: kd2346751@gmail.com
License: UNKNOWN
Platform: UNKNOWN
Classifier: Programming Language :: Python :: 3.8
Classifier: License :: OSI Approved :: GNU General Public License v3 (GPLv3)
Classifier: Operating System :: OS Independent
Classifier: Programming Language :: Python :: 2
Classifier: Programming Language :: Python :: 2.7
Classifier: Programming Language :: Python :: 3
Classifier: Programming Language :: Python :: 3.4
Classifier: Programming Language :: Python :: 3.5
